notagain.py
notagain-0.3.dist-info/LICENSE
notagain-0.3.dist-info/WHEEL
notagain-0.3.dist-info/METADATA
notagain-0.3.dist-info/RECORD
