Metadata-Version: 2.1
Name: notagain
Version: 0.3
Summary: Memory and disk cache for functions
Home-page: https://github.com/matiasbattocchia/notagain
License: BSD-3-Clause
Author: Matías Battocchia
Author-email: battox@gmail.com
